[
  {
    "name": "Japan",
    "compositeScore": 5.99,
    "costLevel": 6,
    "qualityLevel": 9,
    "costOfLivingIndex": 47.5,
    "qualityOfLifeIndex": 185.6,
    "safetyIndex": 77.2,
    "healthcareIndex": 80.1,
    "pollutionIndex": 37.8,
    "climateIndex": 83.8
  },
  {
    "name": "Netherlands",
    "compositeScore": 5.83,
    "costLevel": 8,
    "qualityLevel": 10,
    "costOfLivingIndex": 73.4,
    "qualityOfLifeIndex": 213.6,
    "safetyIndex": 74.5,
    "healthcareIndex": 81.5,
    "pollutionIndex": 20.9,
    "climateIndex": 86.9
  },
  {
    "name": "Taiwan",
    "compositeScore": 5.78,
    "costLevel": 6,
    "qualityLevel": 7,
    "costOfLivingIndex": 49.7,
    "qualityOfLifeIndex": 155.5,
    "safetyIndex": 83.0,
    "healthcareIndex": 87.1,
    "pollutionIndex": 64.1,
    "climateIndex": 83.9
  },
  {
    "name": "Oman",
    "compositeScore": 5.77,
    "costLevel": 6,
    "qualityLevel": 10,
    "costOfLivingIndex": 43.6,
    "qualityOfLifeIndex": 207.6,
    "safetyIndex": 81.6,
    "healthcareIndex": 63.5,
    "pollutionIndex": 36.5,
    "climateIndex": 71.3
  },
  {
    "name": "Denmark",
    "compositeScore": 5.64,
    "costLevel": 8,
    "qualityLevel": 10,
    "costOfLivingIndex": 78.9,
    "qualityOfLifeIndex": 212.2,
    "safetyIndex": 73.8,
    "healthcareIndex": 77.2,
    "pollutionIndex": 22.7,
    "climateIndex": 81.2
  },
  {
    "name": "Estonia",
    "compositeScore": 5.53,
    "costLevel": 7,
    "qualityLevel": 9,
    "costOfLivingIndex": 59.7,
    "qualityOfLifeIndex": 190.7,
    "safetyIndex": 76.8,
    "healthcareIndex": 75.2,
    "pollutionIndex": 16.1,
    "climateIndex": 71.2
  },
  {
    "name": "Finland",
    "compositeScore": 5.48,
    "costLevel": 8,
    "qualityLevel": 10,
    "costOfLivingIndex": 69.0,
    "qualityOfLifeIndex": 204.4,
    "safetyIndex": 73.5,
    "healthcareIndex": 77.6,
    "pollutionIndex": 11.8,
    "climateIndex": 54.4
  },
  {
    "name": "Qatar",
    "compositeScore": 5.43,
    "costLevel": 7,
    "qualityLevel": 9,
    "costOfLivingIndex": 50.4,
    "qualityOfLifeIndex": 182.7,
    "safetyIndex": 84.8,
    "healthcareIndex": 73.6,
    "pollutionIndex": 60.0,
    "climateIndex": 36.0
  },
  {
    "name": "Spain",
    "compositeScore": 5.41,
    "costLevel": 7,
    "qualityLevel": 9,
    "costOfLivingIndex": 51.6,
    "qualityOfLifeIndex": 185.8,
    "safetyIndex": 62.4,
    "healthcareIndex": 77.2,
    "pollutionIndex": 35.3,
    "climateIndex": 92.8
  },
  {
    "name": "Luxembourg",
    "compositeScore": 5.4,
    "costLevel": 8,
    "qualityLevel": 10,
    "costOfLivingIndex": 78.0,
    "qualityOfLifeIndex": 211.9,
    "safetyIndex": 66.8,
    "healthcareIndex": 74.2,
    "pollutionIndex": 22.7,
    "climateIndex": 82.6
  },
  {
    "name": "Austria",
    "compositeScore": 5.34,
    "costLevel": 8,
    "qualityLevel": 9,
    "costOfLivingIndex": 71.3,
    "qualityOfLifeIndex": 199.8,
    "safetyIndex": 71.5,
    "healthcareIndex": 78.9,
    "pollutionIndex": 20.4,
    "climateIndex": 76.6
  },
  {
    "name": "Portugal",
    "compositeScore": 5.32,
    "costLevel": 6,
    "qualityLevel": 8,
    "costOfLivingIndex": 48.8,
    "qualityOfLifeIndex": 169.5,
    "safetyIndex": 67.0,
    "healthcareIndex": 72.0,
    "pollutionIndex": 29.9,
    "climateIndex": 97.8
  },
  {
    "name": "Slovenia",
    "compositeScore": 5.28,
    "costLevel": 7,
    "qualityLevel": 9,
    "costOfLivingIndex": 54.1,
    "qualityOfLifeIndex": 181.5,
    "safetyIndex": 75.5,
    "healthcareIndex": 66.2,
    "pollutionIndex": 22.7,
    "climateIndex": 80.6
  },
  {
    "name": "Czech Republic",
    "compositeScore": 5.24,
    "costLevel": 7,
    "qualityLevel": 8,
    "costOfLivingIndex": 53.0,
    "qualityOfLifeIndex": 175.3,
    "safetyIndex": 73.6,
    "healthcareIndex": 76.0,
    "pollutionIndex": 33.7,
    "climateIndex": 77.7
  },
  {
    "name": "United Arab Emirates",
    "compositeScore": 5.14,
    "costLevel": 7,
    "qualityLevel": 8,
    "costOfLivingIndex": 55.2,
    "qualityOfLifeIndex": 175.5,
    "safetyIndex": 86.0,
    "healthcareIndex": 70.8,
    "pollutionIndex": 48.3,
    "climateIndex": 43.4
  },
  {
    "name": "Lithuania",
    "compositeScore": 5.02,
    "costLevel": 7,
    "qualityLevel": 8,
    "costOfLivingIndex": 51.2,
    "qualityOfLifeIndex": 178.2,
    "safetyIndex": 66.8,
    "healthcareIndex": 75.4,
    "pollutionIndex": 25.2,
    "climateIndex": 69.9
  },
  {
    "name": "Croatia",
    "compositeScore": 5.01,
    "costLevel": 7,
    "qualityLevel": 8,
    "costOfLivingIndex": 52.4,
    "qualityOfLifeIndex": 176.6,
    "safetyIndex": 75.7,
    "healthcareIndex": 65.1,
    "pollutionIndex": 31.8,
    "climateIndex": 87.1
  },
  {
    "name": "Turkey",
    "compositeScore": 5.01,
    "costLevel": 5,
    "qualityLevel": 7,
    "costOfLivingIndex": 39.2,
    "qualityOfLifeIndex": 142.1,
    "safetyIndex": 58.5,
    "healthcareIndex": 71.3,
    "pollutionIndex": 63.9,
    "climateIndex": 90.0
  },
  {
    "name": "India",
    "compositeScore": 5.0,
    "costLevel": 2,
    "qualityLevel": 6,
    "costOfLivingIndex": 18.9,
    "qualityOfLifeIndex": 122.3,
    "safetyIndex": 55.8,
    "healthcareIndex": 65.5,
    "pollutionIndex": 72.8,
    "climateIndex": 65.2
  },
  {
    "name": "Switzerland",
    "compositeScore": 4.98,
    "costLevel": 10,
    "qualityLevel": 10,
    "costOfLivingIndex": 110.7,
    "qualityOfLifeIndex": 206.2,
    "safetyIndex": 72.6,
    "healthcareIndex": 71.2,
    "pollutionIndex": 24.3,
    "climateIndex": 80.7
  },
  {
    "name": "China",
    "compositeScore": 4.97,
    "costLevel": 5,
    "qualityLevel": 6,
    "costOfLivingIndex": 30.5,
    "qualityOfLifeIndex": 134.8,
    "safetyIndex": 76.9,
    "healthcareIndex": 69.2,
    "pollutionIndex": 76.2,
    "climateIndex": 74.4
  },
  {
    "name": "Germany",
    "compositeScore": 4.95,
    "costLevel": 8,
    "qualityLevel": 9,
    "costOfLivingIndex": 68.7,
    "qualityOfLifeIndex": 196.3,
    "safetyIndex": 61.6,
    "healthcareIndex": 72.4,
    "pollutionIndex": 28.2,
    "climateIndex": 82.9
  },
  {
    "name": "Israel",
    "compositeScore": 4.92,
    "costLevel": 8,
    "qualityLevel": 8,
    "costOfLivingIndex": 79.7,
    "qualityOfLifeIndex": 167.7,
    "safetyIndex": 68.2,
    "healthcareIndex": 73.4,
    "pollutionIndex": 56.5,
    "climateIndex": 93.8
  },
  {
    "name": "Norway",
    "compositeScore": 4.87,
    "costLevel": 9,
    "qualityLevel": 9,
    "costOfLivingIndex": 83.7,
    "qualityOfLifeIndex": 195.4,
    "safetyIndex": 66.7,
    "healthcareIndex": 75.8,
    "pollutionIndex": 19.0,
    "climateIndex": 70.6
  },
  {
    "name": "Saudi Arabia",
    "compositeScore": 4.86,
    "costLevel": 6,
    "qualityLevel": 8,
    "costOfLivingIndex": 43.9,
    "qualityOfLifeIndex": 165.3,
    "safetyIndex": 76.7,
    "healthcareIndex": 62.2,
    "pollutionIndex": 61.7,
    "climateIndex": 38.6
  },
  {
    "name": "South Korea",
    "compositeScore": 4.86,
    "costLevel": 8,
    "qualityLevel": 7,
    "costOfLivingIndex": 61.6,
    "qualityOfLifeIndex": 150.4,
    "safetyIndex": 71.0,
    "healthcareIndex": 82.9,
    "pollutionIndex": 56.6,
    "climateIndex": 71.9
  },
  {
    "name": "Iceland",
    "compositeScore": 4.83,
    "costLevel": 9,
    "qualityLevel": 9,
    "costOfLivingIndex": 97.2,
    "qualityOfLifeIndex": 195.8,
    "safetyIndex": 74.5,
    "healthcareIndex": 69.1,
    "pollutionIndex": 17.0,
    "climateIndex": 68.8
  },
  {
    "name": "Australia",
    "compositeScore": 4.8,
    "costLevel": 8,
    "qualityLevel": 9,
    "costOfLivingIndex": 67.9,
    "qualityOfLifeIndex": 189.6,
    "safetyIndex": 52.5,
    "healthcareIndex": 72.0,
    "pollutionIndex": 27.9,
    "climateIndex": 91.9
  },
  {
    "name": "New Zealand",
    "compositeScore": 4.68,
    "costLevel": 8,
    "qualityLevel": 9,
    "costOfLivingIndex": 60.3,
    "qualityOfLifeIndex": 188.5,
    "safetyIndex": 51.2,
    "healthcareIndex": 68.2,
    "pollutionIndex": 26.5,
    "climateIndex": 97.2
  },
  {
    "name": "Latvia",
    "compositeScore": 4.63,
    "costLevel": 7,
    "qualityLevel": 8,
    "costOfLivingIndex": 52.3,
    "qualityOfLifeIndex": 167.3,
    "safetyIndex": 63.7,
    "healthcareIndex": 63.6,
    "pollutionIndex": 29.1,
    "climateIndex": 76.8
  },
  {
    "name": "Thailand",
    "compositeScore": 4.61,
    "costLevel": 5,
    "qualityLevel": 5,
    "costOfLivingIndex": 38.0,
    "qualityOfLifeIndex": 106.8,
    "safetyIndex": 63.4,
    "healthcareIndex": 77.5,
    "pollutionIndex": 75.6,
    "climateIndex": 68.0
  },
  {
    "name": "Jordan",
    "compositeScore": 4.6,
    "costLevel": 5,
    "qualityLevel": 6,
    "costOfLivingIndex": 39.4,
    "qualityOfLifeIndex": 125.6,
    "safetyIndex": 60.3,
    "healthcareIndex": 65.6,
    "pollutionIndex": 77.1,
    "climateIndex": 91.2
  },
  {
    "name": "Georgia",
    "compositeScore": 4.59,
    "costLevel": 5,
    "qualityLevel": 6,
    "costOfLivingIndex": 33.1,
    "qualityOfLifeIndex": 126.6,
    "safetyIndex": 73.8,
    "healthcareIndex": 56.3,
    "pollutionIndex": 67.8,
    "climateIndex": 88.5
  },
  {
    "name": "Belgium",
    "compositeScore": 4.58,
    "costLevel": 8,
    "qualityLevel": 8,
    "costOfLivingIndex": 68.6,
    "qualityOfLifeIndex": 175.2,
    "safetyIndex": 50.8,
    "healthcareIndex": 76.4,
    "pollutionIndex": 46.8,
    "climateIndex": 86.5
  },
  {
    "name": "Poland",
    "compositeScore": 4.56,
    "costLevel": 6,
    "qualityLevel": 7,
    "costOfLivingIndex": 47.3,
    "qualityOfLifeIndex": 156.1,
    "safetyIndex": 71.3,
    "healthcareIndex": 57.9,
    "pollutionIndex": 55.5,
    "climateIndex": 75.7
  },
  {
    "name": "Slovakia",
    "compositeScore": 4.51,
    "costLevel": 6,
    "qualityLevel": 7,
    "costOfLivingIndex": 49.6,
    "qualityOfLifeIndex": 158.6,
    "safetyIndex": 68.9,
    "healthcareIndex": 58.2,
    "pollutionIndex": 36.8,
    "climateIndex": 73.9
  },
  {
    "name": "Ecuador",
    "compositeScore": 4.5,
    "costLevel": 5,
    "qualityLevel": 6,
    "costOfLivingIndex": 30.9,
    "qualityOfLifeIndex": 128.7,
    "safetyIndex": 38.1,
    "healthcareIndex": 77.7,
    "pollutionIndex": 59.0,
    "climateIndex": 94.5
  },
  {
    "name": "Sweden",
    "compositeScore": 4.5,
    "costLevel": 8,
    "qualityLevel": 9,
    "costOfLivingIndex": 68.0,
    "qualityOfLifeIndex": 189.3,
    "safetyIndex": 52.1,
    "healthcareIndex": 68.3,
    "pollutionIndex": 17.6,
    "climateIndex": 65.0
  },
  {
    "name": "United Kingdom",
    "compositeScore": 4.5,
    "costLevel": 8,
    "qualityLevel": 8,
    "costOfLivingIndex": 67.8,
    "qualityOfLifeIndex": 175.9,
    "safetyIndex": 51.7,
    "healthcareIndex": 72.7,
    "pollutionIndex": 40.5,
    "climateIndex": 87.8
  },
  {
    "name": "United States",
    "compositeScore": 4.5,
    "costLevel": 8,
    "qualityLevel": 9,
    "costOfLivingIndex": 68.8,
    "qualityOfLifeIndex": 186.0,
    "safetyIndex": 50.8,
    "healthcareIndex": 67.0,
    "pollutionIndex": 37.2,
    "climateIndex": 75.8
  },
  {
    "name": "France",
    "compositeScore": 4.47,
    "costLevel": 8,
    "qualityLevel": 8,
    "costOfLivingIndex": 67.7,
    "qualityOfLifeIndex": 169.8,
    "safetyIndex": 44.2,
    "healthcareIndex": 77.0,
    "pollutionIndex": 43.5,
    "climateIndex": 89.6
  },
  {
    "name": "Bulgaria",
    "compositeScore": 4.46,
    "costLevel": 6,
    "qualityLevel": 7,
    "costOfLivingIndex": 41.6,
    "qualityOfLifeIndex": 148.3,
    "safetyIndex": 64.5,
    "healthcareIndex": 58.3,
    "pollutionIndex": 62.6,
    "climateIndex": 81.2
  },
  {
    "name": "Romania",
    "compositeScore": 4.43,
    "costLevel": 6,
    "qualityLevel": 7,
    "costOfLivingIndex": 40.6,
    "qualityOfLifeIndex": 143.0,
    "safetyIndex": 67.2,
    "healthcareIndex": 56.5,
    "pollutionIndex": 58.4,
    "climateIndex": 76.3
  },
  {
    "name": "Kuwait",
    "compositeScore": 4.42,
    "costLevel": 6,
    "qualityLevel": 8,
    "costOfLivingIndex": 42.5,
    "qualityOfLifeIndex": 162.7,
    "safetyIndex": 67.4,
    "healthcareIndex": 58.6,
    "pollutionIndex": 69.4,
    "climateIndex": 20.2
  },
  {
    "name": "Armenia",
    "compositeScore": 4.4,
    "costLevel": 6,
    "qualityLevel": 6,
    "costOfLivingIndex": 40.9,
    "qualityOfLifeIndex": 121.9,
    "safetyIndex": 77.9,
    "healthcareIndex": 59.5,
    "pollutionIndex": 61.3,
    "climateIndex": 63.4
  },
  {
    "name": "Hungary",
    "compositeScore": 4.37,
    "costLevel": 6,
    "qualityLevel": 7,
    "costOfLivingIndex": 46.9,
    "qualityOfLifeIndex": 147.6,
    "safetyIndex": 66.5,
    "healthcareIndex": 54.2,
    "pollutionIndex": 46.2,
    "climateIndex": 79.8
  },
  {
    "name": "Malaysia",
    "compositeScore": 4.36,
    "costLevel": 5,
    "qualityLevel": 6,
    "costOfLivingIndex": 34.0,
    "qualityOfLifeIndex": 135.2,
    "safetyIndex": 52.0,
    "healthcareIndex": 70.7,
    "pollutionIndex": 60.6,
    "climateIndex": 58.1
  },
  {
    "name": "Singapore",
    "compositeScore": 4.35,
    "costLevel": 9,
    "qualityLevel": 7,
    "costOfLivingIndex": 87.7,
    "qualityOfLifeIndex": 158.1,
    "safetyIndex": 77.5,
    "healthcareIndex": 71.9,
    "pollutionIndex": 32.2,
    "climateIndex": 57.5
  },
  {
    "name": "Hong Kong",
    "compositeScore": 4.32,
    "costLevel": 8,
    "qualityLevel": 6,
    "costOfLivingIndex": 75.2,
    "qualityOfLifeIndex": 128.7,
    "safetyIndex": 78.6,
    "healthcareIndex": 66.5,
    "pollutionIndex": 66.2,
    "climateIndex": 83.6
  },
  {
    "name": "Pakistan",
    "compositeScore": 4.31,
    "costLevel": 2,
    "qualityLevel": 4,
    "costOfLivingIndex": 19.6,
    "qualityOfLifeIndex": 98.3,
    "safetyIndex": 57.6,
    "healthcareIndex": 59.5,
    "pollutionIndex": 73.3,
    "climateIndex": 67.1
  },
  {
    "name": "Cyprus",
    "compositeScore": 4.3,
    "costLevel": 7,
    "qualityLevel": 7,
    "costOfLivingIndex": 58.8,
    "qualityOfLifeIndex": 159.6,
    "safetyIndex": 66.7,
    "healthcareIndex": 56.7,
    "pollutionIndex": 55.3,
    "climateIndex": 92.3
  },
  {
    "name": "Mexico",
    "compositeScore": 4.26,
    "costLevel": 6,
    "qualityLevel": 6,
    "costOfLivingIndex": 42.6,
    "qualityOfLifeIndex": 125.3,
    "safetyIndex": 47.1,
    "healthcareIndex": 72.3,
    "pollutionIndex": 58.3,
    "climateIndex": 86.6
  },
  {
    "name": "Canada",
    "compositeScore": 4.22,
    "costLevel": 8,
    "qualityLevel": 8,
    "costOfLivingIndex": 63.0,
    "qualityOfLifeIndex": 172.0,
    "safetyIndex": 54.4,
    "healthcareIndex": 68.6,
    "pollutionIndex": 29.7,
    "climateIndex": 54.9
  },
  {
    "name": "Bosnia And Herzegovina",
    "compositeScore": 4.17,
    "costLevel": 5,
    "qualityLevel": 6,
    "costOfLivingIndex": 38.7,
    "qualityOfLifeIndex": 136.5,
    "safetyIndex": 58.7,
    "healthcareIndex": 54.6,
    "pollutionIndex": 59.9,
    "climateIndex": 82.9
  },
  {
    "name": "North Macedonia",
    "compositeScore": 4.17,
    "costLevel": 5,
    "qualityLevel": 6,
    "costOfLivingIndex": 35.5,
    "qualityOfLifeIndex": 124.2,
    "safetyIndex": 58.6,
    "healthcareIndex": 55.4,
    "pollutionIndex": 79.2,
    "climateIndex": 79.9
  },
  {
    "name": "Tunisia",
    "compositeScore": 4.17,
    "costLevel": 4,
    "qualityLevel": 5,
    "costOfLivingIndex": 29.1,
    "qualityOfLifeIndex": 117.6,
    "safetyIndex": 55.1,
    "healthcareIndex": 56.6,
    "pollutionIndex": 69.5,
    "climateIndex": 94.3
  },
  {
    "name": "Greece",
    "compositeScore": 4.09,
    "costLevel": 7,
    "qualityLevel": 7,
    "costOfLivingIndex": 54.0,
    "qualityOfLifeIndex": 140.8,
    "safetyIndex": 53.8,
    "healthcareIndex": 58.9,
    "pollutionIndex": 49.2,
    "climateIndex": 93.0
  },
  {
    "name": "South Africa",
    "compositeScore": 4.08,
    "costLevel": 5,
    "qualityLevel": 7,
    "costOfLivingIndex": 37.1,
    "qualityOfLifeIndex": 150.9,
    "safetyIndex": 25.5,
    "healthcareIndex": 64.0,
    "pollutionIndex": 56.9,
    "climateIndex": 95.7
  },
  {
    "name": "Panama",
    "compositeScore": 4.03,
    "costLevel": 6,
    "qualityLevel": 6,
    "costOfLivingIndex": 45.5,
    "qualityOfLifeIndex": 120.4,
    "safetyIndex": 57.2,
    "healthcareIndex": 61.2,
    "pollutionIndex": 55.9,
    "climateIndex": 68.2
  },
  {
    "name": "Vietnam",
    "compositeScore": 4.02,
    "costLevel": 4,
    "qualityLevel": 4,
    "costOfLivingIndex": 26.4,
    "qualityOfLifeIndex": 92.5,
    "safetyIndex": 59.9,
    "healthcareIndex": 62.2,
    "pollutionIndex": 83.7,
    "climateIndex": 71.1
  },
  {
    "name": "Italy",
    "compositeScore": 4.01,
    "costLevel": 8,
    "qualityLevel": 7,
    "costOfLivingIndex": 61.4,
    "qualityOfLifeIndex": 152.9,
    "safetyIndex": 52.7,
    "healthcareIndex": 64.9,
    "pollutionIndex": 53.1,
    "climateIndex": 89.8
  },
  {
    "name": "Uruguay",
    "compositeScore": 4.0,
    "costLevel": 7,
    "qualityLevel": 6,
    "costOfLivingIndex": 55.6,
    "qualityOfLifeIndex": 139.1,
    "safetyIndex": 47.5,
    "healthcareIndex": 68.5,
    "pollutionIndex": 42.8,
    "climateIndex": 98.3
  },
  {
    "name": "Azerbaijan",
    "compositeScore": 3.99,
    "costLevel": 5,
    "qualityLevel": 5,
    "costOfLivingIndex": 30.7,
    "qualityOfLifeIndex": 111.1,
    "safetyIndex": 68.4,
    "healthcareIndex": 49.0,
    "pollutionIndex": 72.0,
    "climateIndex": 91.4
  },
  {
    "name": "Serbia",
    "compositeScore": 3.96,
    "costLevel": 6,
    "qualityLevel": 6,
    "costOfLivingIndex": 42.6,
    "qualityOfLifeIndex": 127.6,
    "safetyIndex": 63.0,
    "healthcareIndex": 52.1,
    "pollutionIndex": 65.8,
    "climateIndex": 82.7
  },
  {
    "name": "Argentina",
    "compositeScore": 3.95,
    "costLevel": 6,
    "qualityLevel": 6,
    "costOfLivingIndex": 41.3,
    "qualityOfLifeIndex": 123.4,
    "safetyIndex": 36.8,
    "healthcareIndex": 67.8,
    "pollutionIndex": 50.4,
    "climateIndex": 95.4
  },
  {
    "name": "Ukraine",
    "compositeScore": 3.95,
    "costLevel": 4,
    "qualityLevel": 5,
    "costOfLivingIndex": 28.2,
    "qualityOfLifeIndex": 117.1,
    "safetyIndex": 53.1,
    "healthcareIndex": 55.8,
    "pollutionIndex": 62.2,
    "climateIndex": 71.3
  },
  {
    "name": "Kazakhstan",
    "compositeScore": 3.91,
    "costLevel": 4,
    "qualityLevel": 5,
    "costOfLivingIndex": 29.8,
    "qualityOfLifeIndex": 107.5,
    "safetyIndex": 54.8,
    "healthcareIndex": 60.7,
    "pollutionIndex": 73.0,
    "climateIndex": 34.8
  },
  {
    "name": "Colombia",
    "compositeScore": 3.89,
    "costLevel": 5,
    "qualityLevel": 5,
    "costOfLivingIndex": 31.7,
    "qualityOfLifeIndex": 105.9,
    "safetyIndex": 38.7,
    "healthcareIndex": 68.9,
    "pollutionIndex": 62.2,
    "climateIndex": 82.3
  },
  {
    "name": "Russia",
    "compositeScore": 3.89,
    "costLevel": 5,
    "qualityLevel": 5,
    "costOfLivingIndex": 36.5,
    "qualityOfLifeIndex": 115.6,
    "safetyIndex": 61.8,
    "healthcareIndex": 61.6,
    "pollutionIndex": 58.4,
    "climateIndex": 38.0
  },
  {
    "name": "Philippines",
    "compositeScore": 3.85,
    "costLevel": 5,
    "qualityLevel": 4,
    "costOfLivingIndex": 30.1,
    "qualityOfLifeIndex": 87.1,
    "safetyIndex": 56.5,
    "healthcareIndex": 66.8,
    "pollutionIndex": 72.5,
    "climateIndex": 68.4
  },
  {
    "name": "Costa Rica",
    "compositeScore": 3.83,
    "costLevel": 7,
    "qualityLevel": 6,
    "costOfLivingIndex": 52.9,
    "qualityOfLifeIndex": 127.3,
    "safetyIndex": 46.1,
    "healthcareIndex": 64.8,
    "pollutionIndex": 41.4,
    "climateIndex": 93.1
  },
  {
    "name": "Chile",
    "compositeScore": 3.82,
    "costLevel": 5,
    "qualityLevel": 5,
    "costOfLivingIndex": 39.0,
    "qualityOfLifeIndex": 109.8,
    "safetyIndex": 39.3,
    "healthcareIndex": 63.6,
    "pollutionIndex": 77.3,
    "climateIndex": 95.6
  },
  {
    "name": "Indonesia",
    "compositeScore": 3.82,
    "costLevel": 4,
    "qualityLevel": 4,
    "costOfLivingIndex": 26.1,
    "qualityOfLifeIndex": 91.1,
    "safetyIndex": 53.6,
    "healthcareIndex": 61.2,
    "pollutionIndex": 68.0,
    "climateIndex": 66.5
  },
  {
    "name": "Ireland",
    "compositeScore": 3.82,
    "costLevel": 8,
    "qualityLevel": 8,
    "costOfLivingIndex": 70.6,
    "qualityOfLifeIndex": 167.7,
    "safetyIndex": 51.0,
    "healthcareIndex": 51.2,
    "pollutionIndex": 34.7,
    "climateIndex": 89.5
  },
  {
    "name": "Kenya",
    "compositeScore": 3.79,
    "costLevel": 4,
    "qualityLevel": 4,
    "costOfLivingIndex": 28.9,
    "qualityOfLifeIndex": 99.4,
    "safetyIndex": 44.9,
    "healthcareIndex": 62.2,
    "pollutionIndex": 69.0,
    "climateIndex": 87.1
  },
  {
    "name": "Belarus",
    "compositeScore": 3.76,
    "costLevel": 5,
    "qualityLevel": 6,
    "costOfLivingIndex": 30.5,
    "qualityOfLifeIndex": 135.7,
    "safetyIndex": 51.5,
    "healthcareIndex": 49.6,
    "pollutionIndex": 44.2,
    "climateIndex": 68.5
  },
  {
    "name": "Egypt",
    "compositeScore": 3.75,
    "costLevel": 3,
    "qualityLevel": 4,
    "costOfLivingIndex": 21.6,
    "qualityOfLifeIndex": 81.9,
    "safetyIndex": 53.6,
    "healthcareIndex": 47.9,
    "pollutionIndex": 82.5,
    "climateIndex": 85.3
  },
  {
    "name": "Malta",
    "compositeScore": 3.74,
    "costLevel": 7,
    "qualityLevel": 6,
    "costOfLivingIndex": 56.8,
    "qualityOfLifeIndex": 135.3,
    "safetyIndex": 57.0,
    "healthcareIndex": 53.3,
    "pollutionIndex": 75.7,
    "climateIndex": 97.8
  },
  {
    "name": "Iran",
    "compositeScore": 3.7,
    "costLevel": 3,
    "qualityLevel": 4,
    "costOfLivingIndex": 22.8,
    "qualityOfLifeIndex": 88.0,
    "safetyIndex": 49.2,
    "healthcareIndex": 52.8,
    "pollutionIndex": 75.2,
    "climateIndex": 69.0
  },
  {
    "name": "Sri Lanka",
    "compositeScore": 3.69,
    "costLevel": 5,
    "qualityLevel": 3,
    "costOfLivingIndex": 33.9,
    "qualityOfLifeIndex": 61.0,
    "safetyIndex": 57.6,
    "healthcareIndex": 70.7,
    "pollutionIndex": 58.0,
    "climateIndex": 64.1
  },
  {
    "name": "Lebanon",
    "compositeScore": 3.62,
    "costLevel": 6,
    "qualityLevel": 4,
    "costOfLivingIndex": 41.7,
    "qualityOfLifeIndex": 98.2,
    "safetyIndex": 53.1,
    "healthcareIndex": 63.7,
    "pollutionIndex": 89.3,
    "climateIndex": 94.7
  },
  {
    "name": "Brazil",
    "compositeScore": 3.59,
    "costLevel": 5,
    "qualityLevel": 5,
    "costOfLivingIndex": 30.1,
    "qualityOfLifeIndex": 117.8,
    "safetyIndex": 36.0,
    "healthcareIndex": 59.3,
    "pollutionIndex": 52.8,
    "climateIndex": 92.5
  },
  {
    "name": "Morocco",
    "compositeScore": 3.57,
    "costLevel": 5,
    "qualityLevel": 5,
    "costOfLivingIndex": 31.4,
    "qualityOfLifeIndex": 114.1,
    "safetyIndex": 53.0,
    "healthcareIndex": 46.8,
    "pollutionIndex": 68.6,
    "climateIndex": 90.3
  },
  {
    "name": "Albania",
    "compositeScore": 3.43,
    "costLevel": 6,
    "qualityLevel": 5,
    "costOfLivingIndex": 45.8,
    "qualityOfLifeIndex": 105.6,
    "safetyIndex": 55.9,
    "healthcareIndex": 48.1,
    "pollutionIndex": 77.1,
    "climateIndex": 86.3
  },
  {
    "name": "Puerto Rico",
    "compositeScore": 3.4,
    "costLevel": 8,
    "qualityLevel": 7,
    "costOfLivingIndex": 62.6,
    "qualityOfLifeIndex": 153.1,
    "safetyIndex": 38.6,
    "healthcareIndex": 59.1,
    "pollutionIndex": 47.9,
    "climateIndex": 71.2
  },
  {
    "name": "Peru",
    "compositeScore": 3.18,
    "costLevel": 5,
    "qualityLevel": 4,
    "costOfLivingIndex": 33.5,
    "qualityOfLifeIndex": 92.3,
    "safetyIndex": 33.1,
    "healthcareIndex": 56.9,
    "pollutionIndex": 81.9,
    "climateIndex": 93.3
  },
  {
    "name": "Bangladesh",
    "compositeScore": 2.87,
    "costLevel": 3,
    "qualityLevel": 3,
    "costOfLivingIndex": 22.8,
    "qualityOfLifeIndex": 73.3,
    "safetyIndex": 38.4,
    "healthcareIndex": 42.0,
    "pollutionIndex": 85.4,
    "climateIndex": 72.9
  },
  {
    "name": "Nigeria",
    "compositeScore": 2.45,
    "costLevel": 4,
    "qualityLevel": 2,
    "costOfLivingIndex": 27.7,
    "qualityOfLifeIndex": 50.0,
    "safetyIndex": 33.8,
    "healthcareIndex": 48.3,
    "pollutionIndex": 87.1,
    "climateIndex": 70.7
  },
  {
    "name": "Venezuela",
    "compositeScore": 1.99,
    "costLevel": 5,
    "qualityLevel": 3,
    "costOfLivingIndex": 37.7,
    "qualityOfLifeIndex": 75.2,
    "safetyIndex": 19.6,
    "healthcareIndex": 39.9,
    "pollutionIndex": 73.6,
    "climateIndex": 79.9
  }
]